sphinxnotes_extweb-1.0a0-py3.9-nspkg.pth
sphinxnotes/extweb/__init__.py
sphinxnotes_extweb-1.0a0.dist-info/LICENSE
sphinxnotes_extweb-1.0a0.dist-info/METADATA
sphinxnotes_extweb-1.0a0.dist-info/WHEEL
sphinxnotes_extweb-1.0a0.dist-info/namespace_packages.txt
sphinxnotes_extweb-1.0a0.dist-info/top_level.txt
sphinxnotes_extweb-1.0a0.dist-info/RECORD
