Metadata-Version: 2.1
Name: sphinxnotes-extweb
Version: 1.0a0
Summary: Sphinx extension for embedding external web resources (like video, music, etc)
Home-page: https://sphinx-notes.github.io/extweb
Download-URL: http://pypi.python.org/pypi/sphinxnotes-extweb
Author: Shengyu Zhang
License: BSD
Keywords: documentation,sphinx,web,video,music
Platform: any
Classifier: Development Status :: 5 - Production/Stable
Classifier: Environment :: Console
Classifier: Environment :: Web Environment
Classifier: Environment :: Plugins
Classifier: Intended Audience :: Developers
Classifier: License :: OSI Approved :: BSD License
Classifier: Operating System :: OS Independent
Classifier: Programming Language :: Python
Classifier: Topic :: Documentation
Classifier: Topic :: Utilities
Requires-Python: >=3
License-File: LICENSE
Requires-Dist: Sphinx (>=1.6)
